inference/cli.py
inference/hf_utils.py
inference/http_server.py
inference/openai_protocol.py
inference/server_args.py
inference/tokenizer_manager.py
inference/config/load_config.py
inference/config/model_config.py
inference/engine/async_llm.py
inference/engine/kv_cache.py
inference/engine/sampling_engine.py
inference/metal_ops/__init__.py
inference/metal_ops/add_kernel.metal
inference/metal_ops/loader.py
inference/metal_ops/ops.mm
inference/model_loader/model_loader.py
inference/model_loader/utils.py
inference/models/qwen3.py
inference/models/qwen3continous.py
inference/models/registry.py
macos_serving-0.1.1.dist-info/METADATA
macos_serving-0.1.1.dist-info/WHEEL
macos_serving-0.1.1.dist-info/entry_points.txt
macos_serving-0.1.1.dist-info/RECORD
