Metadata-Version: 2.4
Name: macos-serving
Version: 0.1.1
Summary: Simple LLM continous batching engine implementation with support for optimized macos-inference
Project-URL: Repository, https://github.com/dawid-sliwa/macos-inf
Requires-Python: >=3.11
Requires-Dist: fastapi>=0.115.12
Requires-Dist: huggingface-hub>=0.30.2
Requires-Dist: torch>=2.7.0
Requires-Dist: transformers>=4.51.3
Requires-Dist: uvicorn>=0.34.2
Requires-Dist: uvloop>=0.21.0
